restfulContentManager/__init__.py
restfulContentManager/checkpoints.py
restfulContentManager/manager.py
restfulContentManager/util.py
restfulContentManager-0.1.7.dist-info/DESCRIPTION.rst
restfulContentManager-0.1.7.dist-info/METADATA
restfulContentManager-0.1.7.dist-info/RECORD
restfulContentManager-0.1.7.dist-info/WHEEL
restfulContentManager-0.1.7.dist-info/metadata.json
restfulContentManager-0.1.7.dist-info/top_level.txt
