Metadata-Version: 2.0
Name: restfulContentManager
Version: 0.1.7
Summary: A ContentManager for IPython/Jupyter that queries a restful API for entries.
Home-page: https://github.com/datascienceinc/RestfulContentManager
Author: DataScience
Author-email: dev@datascience.com
License: UNKNOWN
Download-URL: https://github.com/datascienceinc/RestfulContentManager/tarball/0.0.0
Platform: UNKNOWN
Requires-Dist: mixpanel
Requires-Dist: notebook
Requires-Dist: requests
Requires-Dist: tornado
Requires-Dist: traitlets
